goldhand/__init__.py
goldhand/backtest.py
goldhand/helpers.py
goldhand/stocks.py
goldhand/strategy_goldhand_line.py
goldhand/strategy_rsi.py
goldhand/tw.py
goldhand-21.0.dist-info/METADATA
goldhand-21.0.dist-info/WHEEL
goldhand-21.0.dist-info/top_level.txt
goldhand-21.0.dist-info/RECORD
