Metadata-Version: 2.4
Name: goldhand
Version: 21.0
Summary: A package working with financial data
Home-page: https://github.com/misrori/goldhand
Author: Mihaly
Author-email: ormraat.pte@gmail.com
License: MIT
Requires-Dist: pandas
Requires-Dist: plotly
Requires-Dist: scipy
Requires-Dist: numpy
Requires-Dist: numba
Requires-Dist: requests
Requires-Dist: tqdm
Requires-Dist: yfinance<1.0
Requires-Dist: ipython
Dynamic: author
Dynamic: author-email
Dynamic: description
Dynamic: description-content-type
Dynamic: home-page
Dynamic: license
Dynamic: requires-dist
Dynamic: summary
